Workbook

Sheet Dashboard
A1: Financial Monitoring Dashboard | B1: Financial Monitoring Dashboard | C1: Financial Monitoring Dashboard | D1: Financial Monitoring Dashboard | E1: Financial Monitoring Dashboard | F1: Financial Monitoring Dashboard | G1: Financial Monitoring Dashboard | H1: Financial Monitoring Dashboard | I1: Financial Monitoring Dashboard | J1: Financial Monitoring Dashboard | K1: Financial Monitoring Dashboard | L1: Financial Monitoring Dashboard | M1: Financial Monitoring Dashboard | N1: Financial Monitoring Dashboard
A2: คณะสัตวแพทยศาสตร์ มหาวิทยาลัยเชียงใหม่ | Executive Financial Dashboard
A3: ="Selected: FY "&Config!B4&" | "&Config!B5&" | "&Config!B6&" Refresh: "&TEXT(Config!B7,"dd mmm yyyy") -> Selected: FY 69 | Q2 | ทั้งหมด Refresh: 13 Jul 2026
A5: Interactive controls — edit selections in Config (dropdowns) | B5: Interactive controls — edit selections in Config (dropdowns) | C5: Interactive controls — edit selections in Config (dropdowns) | D5: Interactive controls — edit selections in Config (dropdowns) | E5: Interactive controls — edit selections in Config (dropdowns) | F5: Interactive controls — edit selections in Config (dropdowns) | G5: Interactive controls — edit selections in Config (dropdowns) | H5: Interactive controls — edit selections in Config (dropdowns) | I5: Interactive controls — edit selections in Config (dropdowns) | J5: Interactive controls — edit selections in Config (dropdowns) | K5: Interactive controls — edit selections in Config (dropdowns) | L5: Interactive controls — edit selections in Config (dropdowns) | M5: Interactive controls — edit selections in Config (dropdowns) | N5: Interactive controls — edit selections in Config (dropdowns)
A6: Fiscal Year | B6: Quarter | C6: Unit | D6: Liquidity status | E6: Revenue achievement | F6: Expense utilization
A7: =Config!B4 -> 69 | B7: =Config!B5 -> Q2 | C7: =Config!B6 -> ทั้งหมด | D7: =IF(Dashboard_Data!B9>=Config!B9,"ดี",IF(Dashboard_Data!B9>=Config!B8,"เฝ้าระวัง","วิกฤต")) -> วิกฤต | E7: =IF(Dashboard_Data!B12>=Config!B10,"ดี","เฝ้าระวัง") -> เฝ้าระวัง | F7: =IF(Dashboard_Data!B15<=Config!B11,"ดี","เฝ้าระวัง") -> ดี
A8: Financial Liquidity | B8: Financial Liquidity | C8: Total Revenue | D8: Total Revenue | E8: Total Expense | F8: Total Expense | G8: Operating Result | H8: Operating Result | I8: Operating Margin | J8: Operating Margin | K8: Budget Achievement | L8: Budget Achievement
A9: =Dashboard_Data!B9 -> 0.35268405 | C9: =Dashboard_Data!B4 -> 73281544 | E9: =Dashboard_Data!B5 -> 57694327 | G9: =Dashboard_Data!B6 -> 15587217 | I9: =Dashboard_Data!B7 -> 0.21270317 | K9: =Dashboard_Data!B12 -> 0.42685212
A13: Revenue, Expense & Operating Result Trend (ล้านบาท) | B13: Revenue, Expense & Operating Result Trend (ล้านบาท) | C13: Revenue, Expense & Operating Result Trend (ล้านบาท) | D13: Revenue, Expense & Operating Result Trend (ล้านบาท) | E13: Revenue, Expense & Operating Result Trend (ล้านบาท) | F13: Revenue, Expense & Operating Result Trend (ล้านบาท) | G13: Revenue, Expense & Operating Result Trend (ล้านบาท) | H13: Budget vs Actual (ล้านบาท) | I13: Budget vs Actual (ล้านบาท) | J13: Budget vs Actual (ล้านบาท) | K13: Budget vs Actual (ล้านบาท) | L13: Budget vs Actual (ล้านบาท) | M13: Budget vs Actual (ล้านบาท) | N13: Budget vs Actual (ล้านบาท)
A14: =Dashboard_Data!D3 -> Period | B14: =Dashboard_Data!E3 -> Revenue | C14: =Dashboard_Data!F3 -> Expense | D14: =Dashboard_Data!G3 -> Operating Result | H14: =Dashboard_Data!I3 -> Budget vs Actual | I14: =Dashboard_Data!J3 -> Budget | J14: =Dashboard_Data!K3 -> Actual
A15: =Dashboard_Data!D4 -> Q3/68 | B15: =Dashboard_Data!E4 -> 90260853 | C15: =Dashboard_Data!F4 -> 84229576 | D15: =Dashboard_Data!G4 -> 6031277 | H15: =Dashboard_Data!I4 -> Revenue | I15: =Dashboard_Data!J4 -> 171825100 | J15: =Dashboard_Data!K4 -> 73281544
A16: =Dashboard_Data!D5 -> Q4/68 | B16: =Dashboard_Data!E5 -> 131408229 | C16: =Dashboard_Data!F5 -> 127865373 | D16: =Dashboard_Data!G5 -> 3542856 | H16: =Dashboard_Data!I5 -> Expense | I16: =Dashboard_Data!J5 -> 165565500 | J16: =Dashboard_Data!K5 -> 57694327
A17: =Dashboard_Data!D6 -> Q1/69 | B17: =Dashboard_Data!E6 -> 46683658 | C17: =Dashboard_Data!F6 -> 51712260 | D17: =Dashboard_Data!G6 -> -5028602
A18: =Dashboard_Data!D7 -> Q2/69 | B18: =Dashboard_Data!E7 -> 73281544 | C18: =Dashboard_Data!F7 -> 57694327 | D18: =Dashboard_Data!G7 -> 15587217
A29: Performance by Unit — Q2/69 | B29: Performance by Unit — Q2/69 | C29: Performance by Unit — Q2/69 | D29: Performance by Unit — Q2/69 | E29: Performance by Unit — Q2/69 | F29: Performance by Unit — Q2/69 | G29: Performance by Unit — Q2/69 | H29: Government Budget & Liquidity | I29: Government Budget & Liquidity | J29: Government Budget & Liquidity | K29: Government Budget & Liquidity | L29: Government Budget & Liquidity | M29: Government Budget & Liquidity | N29: Government Budget & Liquidity
A30: =รายรับรายจ่ายกำไร_ย่อย!A1 -> Sub-unit (A) | B30: =รายรับรายจ่ายกำไร_ย่อย!B1 -> Revenue (B) | C30: =รายรับรายจ่ายกำไร_ย่อย!C1 -> Expenses (C) | D30: =รายรับรายจ่ายกำไร_ย่อย!D1 -> Net Profit (D) | E30: =รายรับรายจ่ายกำไร_ย่อย!F1 -> proportion | H30: Metric | I30: Value | J30: Status
A31: =รายรับรายจ่ายกำไร_ย่อย!A2 -> สำนักงาน คณะสัตวแพทยศาสตร์ | B31: =รายรับรายจ่ายกำไร_ย่อย!B2 -> 18542474 | C31: =รายรับรายจ่ายกำไร_ย่อย!C2 -> 14354999 | D31: =รายรับรายจ่ายกำไร_ย่อย!D2 -> 4187475 | E31: =รายรับรายจ่ายกำไร_ย่อย!F2 -> 1.2917085 | H31: Government Budget | I31: =SUMIFS(Data_Clean!$K$3:$K$1000,Data_Clean!$H$3:$H$1000,"Government Budget",Data_Clean!$A$3:$A$1000,Config!$B$4,Data_Clean!$B$3:$B$1000,Config!$B$5) -> 207098179
A32: =รายรับรายจ่ายกำไร_ย่อย!A3 -> ศูนย์การเรียนรู้และส่งเสริมสุขภาพสัตว์ภาคเหนือ(NOVEL) | B32: =รายรับรายจ่ายกำไร_ย่อย!B3 -> 39787921 | C32: =รายรับรายจ่ายกำไร_ย่อย!C3 -> 31034819 | D32: =รายรับรายจ่ายกำไร_ย่อย!D3 -> 8753102 | E32: =รายรับรายจ่ายกำไร_ย่อย!F3 -> 1.2820413 | H32: Government Actual | I32: =SUMIFS(Data_Clean!$K$3:$K$1000,Data_Clean!$H$3:$H$1000,"Government Actual",Data_Clean!$A$3:$A$1000,Config!$B$4,Data_Clean!$B$3:$B$1000,Config!$B$5) -> 89248624
A33: =รายรับรายจ่ายกำไร_ย่อย!A4 -> (โรงพยาบาลสัตว์แม่ออน) | B33: =รายรับรายจ่ายกำไร_ย่อย!B4 -> 1762983 | C33: =รายรับรายจ่ายกำไร_ย่อย!C4 -> 1511583 | D33: =รายรับรายจ่ายกำไร_ย่อย!D4 -> 251400 | E33: =รายรับรายจ่ายกำไร_ย่อย!F4 -> 1.1663157 | H33: Budget Utilization | I33: =IFERROR(I32/I31,0) -> 0.43094838 | J33: =IF(I33<=Config!B11,"ดี","เฝ้าระวัง") -> ดี
A34: =รายรับรายจ่ายกำไร_ย่อย!A5 -> โรงพยาบาลสัตว์ใหญ่และปศุสัตว์ | B34: =รายรับรายจ่ายกำไร_ย่อย!B5 -> 1008535 | C34: =รายรับรายจ่ายกำไร_ย่อย!C5 -> 1002935 | D34: =รายรับรายจ่ายกำไร_ย่อย!D5 -> 5600 | E34: =รายรับรายจ่ายกำไร_ย่อย!F5 -> 1.0055836 | H34: Liquidity | I34: =Dashboard_Data!B9 -> 0.35268405 | J34: =IF(I34>=Config!B9,"ดี",IF(I34>=Config!B8,"เฝ้าระวัง","วิกฤต")) -> วิกฤต
A35: =รายรับรายจ่ายกำไร_ย่อย!A6 -> ศูนย์สุขภาพช้างและสัตว์ป่า | B35: =รายรับรายจ่ายกำไร_ย่อย!B6 -> 1044605 | C35: =รายรับรายจ่ายกำไร_ย่อย!C6 -> 396333 | D35: =รายรับรายจ่ายกำไร_ย่อย!D6 -> 648272 | E35: =รายรับรายจ่ายกำไร_ย่อย!F6 -> 2.6356751 | H35: Management note | I35: Thresholds may be edited in Config
A36: =รายรับรายจ่ายกำไร_ย่อย!A7 -> ศูนย์ชันเวชศาสตร์ชันสูตรและนวัตกรรมด้านสุขภาพสัตว์ | B36: =รายรับรายจ่ายกำไร_ย่อย!B7 -> 2741058 | C36: =รายรับรายจ่ายกำไร_ย่อย!C7 -> 2740822 | D36: =รายรับรายจ่ายกำไร_ย่อย!D7 -> 236 | E36: =รายรับรายจ่ายกำไร_ย่อย!F7 -> 1.0000861
A37: =รายรับรายจ่ายกำไร_ย่อย!A8 -> ศูนย์ความเป็นเลิศด้านเวชศาสตร์แมว | B37: =รายรับรายจ่ายกำไร_ย่อย!B8 -> 0 | C37: =รายรับรายจ่ายกำไร_ย่อย!C8 -> 0 | D37: =รายรับรายจ่ายกำไร_ย่อย!D8 -> 0 | E37: =รายรับรายจ่ายกำไร_ย่อย!F8 -> 0
A38: =รายรับรายจ่ายกำไร_ย่อย!A9 -> Pet CMU (กลุ่มงานบ่มเพาะวิสาหกิจทางสัตวแพทย์) | B38: =รายรับรายจ่ายกำไร_ย่อย!B9 -> 7351957 | C38: =รายรับรายจ่ายกำไร_ย่อย!C9 -> 4155836 | D38: =รายรับรายจ่ายกำไร_ย่อย!D9 -> 3196121 | E38: =รายรับรายจ่ายกำไร_ย่อย!F9 -> 1.7690681
A39: =รายรับรายจ่ายกำไร_ย่อย!A10 -> ศูนย์สัตวแพทย์สาธารณสุขและอาหารปลอดภัยเอเชียแปซิฟิก | B39: =รายรับรายจ่ายกำไร_ย่อย!B10 -> 11985 | C39: =รายรับรายจ่ายกำไร_ย่อย!C10 -> 189641 | D39: =รายรับรายจ่ายกำไร_ย่อย!D10 -> -177656 | E39: =รายรับรายจ่ายกำไร_ย่อย!F10 -> 0.063198359
A40: =รายรับรายจ่ายกำไร_ย่อย!A11 -> ศูนย์เฝ้าระวังสุขภาพหนึ่งเดียว PODD | B40: =รายรับรายจ่ายกำไร_ย่อย!B11 -> 1029558 | C40: =รายรับรายจ่ายกำไร_ย่อย!C11 -> 2307358 | D40: =รายรับรายจ่ายกำไร_ย่อย!D11 -> -1277800 | E40: =รายรับรายจ่ายกำไร_ย่อย!F11 -> 0.44620644
A41: =รายรับรายจ่ายกำไร_ย่อย!A12 -> สำนักงานโรงพยาบาลสัตว์(ศรีบัวบาน) | B41: =รายรับรายจ่ายกำไร_ย่อย!B12 -> 0 | C41: =รายรับรายจ่ายกำไร_ย่อย!C12 -> 0 | D41: =รายรับรายจ่ายกำไร_ย่อย!D12 -> 0 | E41: =รายรับรายจ่ายกำไร_ย่อย!F12 -> 0

Sheet งบดุล
A1: Quarter (A) | B1: Current Assets | C1: Non-Current Assets | D1: Liabilities | E1: Financial Liquidity | F1: proportion
A2: Q2/69 | B2: 97630000 | C2: 630450000 | D2: 276820000 | E2: 0.35 : 1 | F2: =B2/D2 -> 0.35268405
A3: Q1/69 | B3: 109300000 | C3: 606210000 | D3: 258040000 | E3: 0.42 : 1 | F3: =B3/D3 -> 0.42357774
A4: Q4/68 | B4: 133880000 | C4: 597120000 | D4: 268960000 | E4: 0.50 : 1 | F4: =B4/D4 -> 0.49776919
A5: Q3/68 | B5: 91620000 | C5: 597150000 | D5: 260360000 | E5: 0.35 : 1 | F5: =B5/D5 -> 0.35189737

Sheet รายรับรายจ่ายกำไร
A1: Quarter (A) | B1: Revenue (B) | C1: Expenses (C) | D1: Net Profit (D) | E1: Current_Ratio (E) | F1: proportion
A2: Q2/69 | B2: 73281544 | C2: 57694327 | D2: =B2-C2 -> 15587217 | E2: 1.27 : 1 | F2: =B2/C2 -> 1.270169
A3: Q1/69 | B3: 46683658 | C3: 51712260 | D3: =B3-C3 -> -5028602 | E3: 0.90 : 1 | F3: =B3/C3 -> 0.90275803
A4: Q4/68 | B4: 131408229 | C4: 127865373 | D4: =B4-C4 -> 3542856 | E4: 1.02 : 1 | F4: =B4/C4 -> 1.0277077
A5: Q3/68 | B5: 90260853 | C5: 84229576 | D5: =B5-C5 -> 6031277 | E5: 1.07 : 1 | F5: =B5/C5 -> 1.0716052

Sheet รายรับรายจ่ายกำไร_ย่อย
A1: Sub-unit (A) | B1: Revenue (B) | C1: Expenses (C) | D1: Net Profit (D) | E1: Current_Ratio (E) | F1: proportion
A2: สำนักงาน คณะสัตวแพทยศาสตร์ | B2: 18542474 | C2: 14354999 | D2: =B2-C2 -> 4187475 | E2: 1.29 : 1 | F2: =B2/C2 -> 1.2917085
A3: ศูนย์การเรียนรู้และส่งเสริมสุขภาพสัตว์ภาคเหนือ(NOVEL) | B3: 39787921 | C3: 31034819 | D3: =B3-C3 -> 8753102 | E3: 1.28 : 1 | F3: =B3/C3 -> 1.2820413
A4: (โรงพยาบาลสัตว์แม่ออน) | B4: 1762983 | C4: 1511583 | D4: =B4-C4 -> 251400 | E4: 1.17 : 1 | F4: =B4/C4 -> 1.1663157
A5: โรงพยาบาลสัตว์ใหญ่และปศุสัตว์ | B5: 1008535 | C5: 1002935 | D5: =B5-C5 -> 5600 | E5: 1.01 : 1 | F5: =B5/C5 -> 1.0055836
A6: ศูนย์สุขภาพช้างและสัตว์ป่า | B6: 1044605 | C6: 396333 | D6: =B6-C6 -> 648272 | E6: 2.64 : 1 | F6: =B6/C6 -> 2.6356751
A7: ศูนย์ชันเวชศาสตร์ชันสูตรและนวัตกรรมด้านสุขภาพสัตว์ | B7: 2741058 | C7: 2740822 | D7: =B7-C7 -> 236 | E7: 1 : 1 | F7: =B7/C7 -> 1.0000861
A8: ศูนย์ความเป็นเลิศด้านเวชศาสตร์แมว | B8: 0 | C8: 0 | D8: =B8-C8 -> 0 | E8: 0 | F8: 0
A9: Pet CMU (กลุ่มงานบ่มเพาะวิสาหกิจทางสัตวแพทย์) | B9: 7351957 | C9: 4155836 | D9: =B9-C9 -> 3196121 | E9: 1.77 : 1 | F9: =B9/C9 -> 1.7690681
A10: ศูนย์สัตวแพทย์สาธารณสุขและอาหารปลอดภัยเอเชียแปซิฟิก | B10: 11985 | C10: 189641 | D10: =B10-C10 -> -177656 | E10: 0.06 : 1 | F10: =B10/C10 -> 0.063198359
A11: ศูนย์เฝ้าระวังสุขภาพหนึ่งเดียว PODD | B11: 1029558 | C11: 2307358 | D11: =B11-C11 -> -1277800 | E11: 0.45 : 1 | F11: =B11/C11 -> 0.44620644
A12: สำนักงานโรงพยาบาลสัตว์(ศรีบัวบาน) | B12: 0 | C12: 0 | D12: =B12-C12 -> 0 | E12: 0 | F12: 0

Sheet ประมาณการรายรับกับรายรับจริง_รว
A1: คณะสัตวแพทย์ | B1: Budgeted Revenue | C1: Revenue Q2 | D1: Percentage(%)
A2: Total | B2: 171825100 | C2: 73281544 | D2: =ตาราง3[Revenue Q2]/ตาราง3[Budgeted Revenue] -> 0.42648917

Sheet ประมาณการรายรับกับรายรับจริง_แย
A1: Sub-unit (A) | B1: Budgeted Revenue | C1: Revenue Q2 | D1: Percentage(%)
A2: สำนักงาน คณะสัตวแพทยศาสตร์ | B2: 28518000 | C2: 18542474 | D2: =C2/B2 -> 0.65020247
A3: ศูนย์การเรียนรู้และส่งเสริมสุขภาพสัตว์ภาคเหนือ(NOVEL) | B3: 114900000 | C3: 39787921 | D3: =C3/B3 -> 0.34628304
A4: (โรงพยาบาลสัตว์แม่ออน) | B4: 3449600 | C4: 1762983 | D4: =C4/B4 -> 0.51106882
A5: โรงพยาบาลสัตว์ใหญ่และปศุสัตว์ | B5: 2176700 | C5: 1008535 | D5: =C5/B5 -> 0.46333211
A6: ศูนย์สุขภาพช้างและสัตว์ป่า | B6: 2173300 | C6: 1044605 | D6: =C6/B6 -> 0.48065384
A7: ศูนย์ชันเวชศาสตร์ชันสูตรและนวัตกรรมด้านสุขภาพสัตว์ | B7: 7074000 | C7: 2741058 | D7: =C7/B7 -> 0.38748346
A8: ศูนย์ความเป็นเลิศด้านเวชศาสตร์แมว | B8: 0 | C8: 0 | D8: 0
A9: Pet CMU (กลุ่มงานบ่มเพาะวิสาหกิจทางสัตวแพทย์) | B9: 7959800 | C9: 7351957 | D9: =C9/B9 -> 0.9236359
A10: ศูนย์สัตวแพทย์สาธารณสุขและอาหารปลอดภัยเอเชียแปซิฟิก | B10: 526500 | C10: 11985 | D10: =C10/B10 -> 0.022763533
A11: ศูนย์เฝ้าระวังสุขภาพหนึ่งเดียว PODD | B11: 4200000 | C11: 1029558 | D11: =C11/B11 -> 0.24513286
A12: สำนักงานโรงพยาบาลสัตว์(ศรีบัวบาน) | B12: 700000 | C12: 0 | D12: =C12/B12 -> 0

Sheet ประมาณการรายจ่ายกับรายจ่ายจริงร
A1: คณะสัตวแพทย์ | B1: Budgeted Revenue | C1: Revenue Q2 | D1: Percentage(%)
A2: Total | B2: 165565500 | C2: 57694327 | D2: =ตาราง5[Revenue Q2]/ตาราง5[Budgeted Revenue] -> 0.34846829

Sheet ประมาณการรายจ่ายกับรายจ่ายจริงแ
A1: Sub-unit (A) | B1: Budgeted Expenses | C1: Expenses Q2 | D1: Percentage(%)
A2: สำนักงาน คณะสัตวแพทยศาสตร์ | B2: 29638800 | C2: 14354999 | D2: =C2/B2 -> 0.48433132
A3: ศูนย์การเรียนรู้และส่งเสริมสุขภาพสัตว์ภาคเหนือ(NOVEL) | B3: 110400000 | C3: 31034819 | D3: =C3/B3 -> 0.28111249
A4: (โรงพยาบาลสัตว์แม่ออน) | B4: 3200000 | C4: 1511583 | D4: =C4/B4 -> 0.47236969
A5: โรงพยาบาลสัตว์ใหญ่และปศุสัตว์ | B5: 2100000 | C5: 1002935 | D5: =C5/B5 -> 0.4775881
A6: ศูนย์สุขภาพช้างและสัตว์ป่า | B6: 1426100 | C6: 396333 | D6: =C6/B6 -> 0.27791389
A7: ศูนย์ชันเวชศาสตร์ชันสูตรและนวัตกรรมด้านสุขภาพสัตว์ | B7: 6366600 | C7: 2740822 | D7: =C7/B7 -> 0.43050011
A8: ศูนย์ความเป็นเลิศด้านเวชศาสตร์แมว | B8: 0 | C8: 0 | D8: 0
A9: Pet CMU (กลุ่มงานบ่มเพาะวิสาหกิจทางสัตวแพทย์) | B9: 7163800 | C9: 4155836 | D9: =C9/B9 -> 0.58011614
A10: ศูนย์สัตวแพทย์สาธารณสุขและอาหารปลอดภัยเอเชียแปซิฟิก | B10: 500000 | C10: 189641 | D10: =C10/B10 -> 0.379282
A11: ศูนย์เฝ้าระวังสุขภาพหนึ่งเดียว PODD | B11: 4000000 | C11: 2307358 | D11: =C11/B11 -> 0.5768395
A12: สำนักงานโรงพยาบาลสัตว์(ศรีบัวบาน) | B12: 500000 | C12: 0 | D12: =C12/B12 -> 0

Sheet งบประมาณแผ่นดิน
A1: คณะสัตวแพทย์ | B1: Budgeted Expenses | C1: Expenses Q2 | D1: Percentage(%)
A2: Total | B2: 207098179 | C2: 89248624 | D2: =ตาราง7[Expenses Q2]/ตาราง7[[Budgeted Expenses ]] -> 0.43094838

Sheet งบแผ่นดินแยกหมวด
A1: คณะสัตวแพทย์ | B1: Budgeted Expenses | C1: Expenses Q2 | D1: Percentage(%)
A2: Equipments | B2: 119046379 | C2: 60616531 | D2: =ตาราง8[[#This Row],[Expenses Q2]]/ตาราง8[[#This Row],[Budgeted Expenses ]] -> 0.50918416
A3: Construction | B3: 88051800 | C3: 28632093 | D3: =ตาราง8[[#This Row],[Expenses Q2]]/ตาราง8[[#This Row],[Budgeted Expenses ]] -> 0.32517328

Sheet Data_Audit
A1: Data Audit — Vet CMU Financial Workbook | B1: Data Audit — Vet CMU Financial Workbook | C1: Data Audit — Vet CMU Financial Workbook | D1: Data Audit — Vet CMU Financial Workbook | E1: Data Audit — Vet CMU Financial Workbook | F1: Data Audit — Vet CMU Financial Workbook | G1: Data Audit — Vet CMU Financial Workbook | H1: Data Audit — Vet CMU Financial Workbook
A2: Worksheet | B2: Used Range | C2: Rows | D2: Columns | E2: Primary data | F2: Time level | G2: Issues found | H2: Dashboard source
A3: Dashboard | B3: B2:D4 | C3: 3 | D3: 3 | E3: Blank placeholder dashboard | F3: N/A | G3: Blank source dashboard sheet | H3: Rebuilt as Executive Dashboard
A4: งบดุล | B4: A1:F5 | C4: 5 | D4: 6 | E4: Assets, liabilities, financial liquidity | F4: Quarter (Q3/68–Q2/69) | G4: Liquidity text plus numeric proportion; one formula | H4: Liquidity KPI and trend
A5: รายรับรายจ่ายกำไร | B5: A1:F5 | C5: 5 | D5: 6 | E5: Revenue, expenses, net profit | F5: Quarter (Q3/68–Q2/69) | G5: Period stored newest-first; one formula | H5: Financial trend and KPIs
A6: รายรับรายจ่ายกำไร_ย่อย | B6: A1:F12 | C6: 12 | D6: 6 | E6: Revenue / expense by sub-unit | F6: Q2/69 snapshot | G6: Zero-value units; ratio is revenue / expense | H6: Unit performance
A7: ประมาณการรายรับกับรายรับจริง_รว | B7: A1:D2 | C7: 2 | D7: 4 | E7: Faculty revenue budget vs actual | F7: Q2/69 | G7: Percentage formula evaluates #NAME? in current engine | H7: Revenue budget KPI (source values used)
A8: ประมาณการรายรับกับรายรับจริง_แย | B8: A1:D12 | C8: 12 | D8: 4 | E8: Unit revenue budget vs actual | F8: Q2/69 | G8: Zero budgets exist; use IFERROR | H8: Unit budget achievement
A9: ประมาณการรายจ่ายกับรายจ่ายจริงร | B9: A1:D2 | C9: 2 | D9: 4 | E9: Faculty expense budget vs actual | F9: Q2/69 | G9: Header says Revenue although values are expenses; percentage #NAME? | H9: Expense utilization KPI
A10: ประมาณการรายจ่ายกับรายจ่ายจริงแ | B10: A1:D12 | C10: 12 | D10: 4 | E10: Unit expense budget vs actual | F10: Q2/69 | G10: Zero budgets exist; use IFERROR | H10: Unit expense utilization
A11: งบประมาณแผ่นดิน | B11: A1:D2 | C11: 2 | D11: 4 | E11: Government budget and spend | F11: Q2/69 | G11: Percentage formula evaluates #NAME? in current engine | H11: Government budget KPI
A12: งบแผ่นดินแยกหมวด | B12: A1:D3 | C12: 3 | D12: 4 | E12: Equipment and construction budget | F12: Q2/69 | G12: Percentage formulas evaluate #NAME? in current engine | H12: Government budget detail

Sheet Data_Clean
A1: Data_Clean — Standardized Financial Facts (formula-linked to original sheets) | B1: Data_Clean — Standardized Financial Facts (formula-linked to original sheets) | C1: Data_Clean — Standardized Financial Facts (formula-linked to original sheets) | D1: Data_Clean — Standardized Financial Facts (formula-linked to original sheets) | E1: Data_Clean — Standardized Financial Facts (formula-linked to original sheets) | F1: Data_Clean — Standardized Financial Facts (formula-linked to original sheets) | G1: Data_Clean — Standardized Financial Facts (formula-linked to original sheets) | H1: Data_Clean — Standardized Financial Facts (formula-linked to original sheets) | I1: Data_Clean — Standardized Financial Facts (formula-linked to original sheets) | J1: Data_Clean — Standardized Financial Facts (formula-linked to original sheets) | K1: Data_Clean — Standardized Financial Facts (formula-linked to original sheets) | L1: Data_Clean — Standardized Financial Facts (formula-linked to original sheets)
A2: FiscalYear | B2: Quarter | C2: Month | D2: MonthNo | E2: Unit | F2: Category | G2: Subcategory | H2: Metric | I2: Budget | J2: Actual | K2: Amount | L2: SourceSheet
A3: 69 | B3: Q2 | D3: 0 | E3: ทั้งหมด | F3: Operating | G3: Total | H3: Revenue | I3: 0 | J3: 0 | K3: =รายรับรายจ่ายกำไร!B2 -> 73281544 | L3: รายรับรายจ่ายกำไร
A4: 69 | B4: Q2 | D4: 0 | E4: ทั้งหมด | F4: Operating | G4: Total | H4: Expense | I4: 0 | J4: 0 | K4: =รายรับรายจ่ายกำไร!C2 -> 57694327 | L4: รายรับรายจ่ายกำไร
A5: 69 | B5: Q2 | D5: 0 | E5: ทั้งหมด | F5: Operating | G5: Total | H5: Operating Result | I5: 0 | J5: 0 | K5: =รายรับรายจ่ายกำไร!D2 -> 15587217 | L5: รายรับรายจ่ายกำไร
A6: 69 | B6: Q2 | D6: 0 | E6: ทั้งหมด | F6: Balance Sheet | G6: Financial Liquidity | H6: Liquidity | I6: 0 | J6: 0 | K6: =งบดุล!F2 -> 0.35268405 | L6: งบดุล
A7: 69 | B7: Q1 | D7: 0 | E7: ทั้งหมด | F7: Operating | G7: Total | H7: Revenue | I7: 0 | J7: 0 | K7: =รายรับรายจ่ายกำไร!B3 -> 46683658 | L7: รายรับรายจ่ายกำไร
A8: 69 | B8: Q1 | D8: 0 | E8: ทั้งหมด | F8: Operating | G8: Total | H8: Expense | I8: 0 | J8: 0 | K8: =รายรับรายจ่ายกำไร!C3 -> 51712260 | L8: รายรับรายจ่ายกำไร
A9: 69 | B9: Q1 | D9: 0 | E9: ทั้งหมด | F9: Operating | G9: Total | H9: Operating Result | I9: 0 | J9: 0 | K9: =รายรับรายจ่ายกำไร!D3 -> -5028602 | L9: รายรับรายจ่ายกำไร
A10: 69 | B10: Q1 | D10: 0 | E10: ทั้งหมด | F10: Balance Sheet | G10: Financial Liquidity | H10: Liquidity | I10: 0 | J10: 0 | K10: =งบดุล!F3 -> 0.42357774 | L10: งบดุล
A11: 68 | B11: Q4 | D11: 0 | E11: ทั้งหมด | F11: Operating | G11: Total | H11: Revenue | I11: 0 | J11: 0 | K11: =รายรับรายจ่ายกำไร!B4 -> 131408229 | L11: รายรับรายจ่ายกำไร
A12: 68 | B12: Q4 | D12: 0 | E12: ทั้งหมด | F12: Operating | G12: Total | H12: Expense | I12: 0 | J12: 0 | K12: =รายรับรายจ่ายกำไร!C4 -> 127865373 | L12: รายรับรายจ่ายกำไร
A13: 68 | B13: Q4 | D13: 0 | E13: ทั้งหมด | F13: Operating | G13: Total | H13: Operating Result | I13: 0 | J13: 0 | K13: =รายรับรายจ่ายกำไร!D4 -> 3542856 | L13: รายรับรายจ่ายกำไร
A14: 68 | B14: Q4 | D14: 0 | E14: ทั้งหมด | F14: Balance Sheet | G14: Financial Liquidity | H14: Liquidity | I14: 0 | J14: 0 | K14: =งบดุล!F4 -> 0.49776919 | L14: งบดุล
A15: 68 | B15: Q3 | D15: 0 | E15: ทั้งหมด | F15: Operating | G15: Total | H15: Revenue | I15: 0 | J15: 0 | K15: =รายรับรายจ่ายกำไร!B5 -> 90260853 | L15: รายรับรายจ่ายกำไร
A16: 68 | B16: Q3 | D16: 0 | E16: ทั้งหมด | F16: Operating | G16: Total | H16: Expense | I16: 0 | J16: 0 | K16: =รายรับรายจ่ายกำไร!C5 -> 84229576 | L16: รายรับรายจ่ายกำไร
A17: 68 | B17: Q3 | D17: 0 | E17: ทั้งหมด | F17: Operating | G17: Total | H17: Operating Result | I17: 0 | J17: 0 | K17: =รายรับรายจ่ายกำไร!D5 -> 6031277 | L17: รายรับรายจ่ายกำไร
A18: 68 | B18: Q3 | D18: 0 | E18: ทั้งหมด | F18: Balance Sheet | G18: Financial Liquidity | H18: Liquidity | I18: 0 | J18: 0 | K18: =งบดุล!F5 -> 0.35189737 | L18: งบดุล
A19: 69 | B19: Q2 | D19: 0 | E19: =รายรับรายจ่ายกำไร_ย่อย!A2 -> สำนักงาน คณะสัตวแพทยศาสตร์ | F19: Operating | G19: Unit | H19: Revenue | I19: 0 | J19: 0 | K19: =รายรับรายจ่ายกำไร_ย่อย!B2 -> 18542474 | L19: รายรับรายจ่ายกำไร_ย่อย
A20: 69 | B20: Q2 | D20: 0 | E20: =รายรับรายจ่ายกำไร_ย่อย!A2 -> สำนักงาน คณะสัตวแพทยศาสตร์ | F20: Operating | G20: Unit | H20: Expense | I20: 0 | J20: 0 | K20: =รายรับรายจ่ายกำไร_ย่อย!C2 -> 14354999 | L20: รายรับรายจ่ายกำไร_ย่อย
A21: 69 | B21: Q2 | D21: 0 | E21: =รายรับรายจ่ายกำไร_ย่อย!A2 -> สำนักงาน คณะสัตวแพทยศาสตร์ | F21: Operating | G21: Unit | H21: Operating Result | I21: 0 | J21: 0 | K21: =รายรับรายจ่ายกำไร_ย่อย!D2 -> 4187475 | L21: รายรับรายจ่ายกำไร_ย่อย
A22: 69 | B22: Q2 | D22: 0 | E22: =ประมาณการรายรับกับรายรับจริง_แย!A2 -> สำนักงาน คณะสัตวแพทยศาสตร์ | F22: Budget | G22: Revenue | H22: Revenue Budget | I22: 0 | J22: 0 | K22: =ประมาณการรายรับกับรายรับจริง_แย!B2 -> 28518000 | L22: ประมาณการรายรับกับรายรับจริง_แย
A23: 69 | B23: Q2 | D23: 0 | E23: =ประมาณการรายรับกับรายรับจริง_แย!A2 -> สำนักงาน คณะสัตวแพทยศาสตร์ | F23: Budget | G23: Revenue | H23: Revenue Actual | I23: 0 | J23: 0 | K23: =ประมาณการรายรับกับรายรับจริง_แย!C2 -> 18542474 | L23: ประมาณการรายรับกับรายรับจริง_แย
A24: 69 | B24: Q2 | D24: 0 | E24: =ประมาณการรายจ่ายกับรายจ่ายจริงแ!A2 -> สำนักงาน คณะสัตวแพทยศาสตร์ | F24: Budget | G24: Expense | H24: Expense Budget | I24: 0 | J24: 0 | K24: =ประมาณการรายจ่ายกับรายจ่ายจริงแ!B2 -> 29638800 | L24: ประมาณการรายจ่ายกับรายจ่ายจริงแ
A25: 69 | B25: Q2 | D25: 0 | E25: =ประมาณการรายจ่ายกับรายจ่ายจริงแ!A2 -> สำนักงาน คณะสัตวแพทยศาสตร์ | F25: Budget | G25: Expense | H25: Expense Actual | I25: 0 | J25: 0 | K25: =ประมาณการรายจ่ายกับรายจ่ายจริงแ!C2 -> 14354999 | L25: ประมาณการรายจ่ายกับรายจ่ายจริงแ
A26: 69 | B26: Q2 | D26: 0 | E26: =รายรับรายจ่ายกำไร_ย่อย!A3 -> ศูนย์การเรียนรู้และส่งเสริมสุขภาพสัตว์ภาคเหนือ(NOVEL) | F26: Operating | G26: Unit | H26: Revenue | I26: 0 | J26: 0 | K26: =รายรับรายจ่ายกำไร_ย่อย!B3 -> 39787921 | L26: รายรับรายจ่ายกำไร_ย่อย
A27: 69 | B27: Q2 | D27: 0 | E27: =รายรับรายจ่ายกำไร_ย่อย!A3 -> ศูนย์การเรียนรู้และส่งเสริมสุขภาพสัตว์ภาคเหนือ(NOVEL) | F27: Operating | G27: Unit | H27: Expense | I27: 0 | J27: 0 | K27: =รายรับรายจ่ายกำไร_ย่อย!C3 -> 31034819 | L27: รายรับรายจ่ายกำไร_ย่อย
A28: 69 | B28: Q2 | D28: 0 | E28: =รายรับรายจ่ายกำไร_ย่อย!A3 -> ศูนย์การเรียนรู้และส่งเสริมสุขภาพสัตว์ภาคเหนือ(NOVEL) | F28: Operating | G28: Unit | H28: Operating Result | I28: 0 | J28: 0 | K28: =รายรับรายจ่ายกำไร_ย่อย!D3 -> 8753102 | L28: รายรับรายจ่ายกำไร_ย่อย
A29: 69 | B29: Q2 | D29: 0 | E29: =ประมาณการรายรับกับรายรับจริง_แย!A3 -> ศูนย์การเรียนรู้และส่งเสริมสุขภาพสัตว์ภาคเหนือ(NOVEL) | F29: Budget | G29: Revenue | H29: Revenue Budget | I29: 0 | J29: 0 | K29: =ประมาณการรายรับกับรายรับจริง_แย!B3 -> 114900000 | L29: ประมาณการรายรับกับรายรับจริง_แย
A30: 69 | B30: Q2 | D30: 0 | E30: =ประมาณการรายรับกับรายรับจริง_แย!A3 -> ศูนย์การเรียนรู้และส่งเสริมสุขภาพสัตว์ภาคเหนือ(NOVEL) | F30: Budget | G30: Revenue | H30: Revenue Actual | I30: 0 | J30: 0 | K30: =ประมาณการรายรับกับรายรับจริง_แย!C3 -> 39787921 | L30: ประมาณการรายรับกับรายรับจริง_แย
A31: 69 | B31: Q2 | D31: 0 | E31: =ประมาณการรายจ่ายกับรายจ่ายจริงแ!A3 -> ศูนย์การเรียนรู้และส่งเสริมสุขภาพสัตว์ภาคเหนือ(NOVEL) | F31: Budget | G31: Expense | H31: Expense Budget | I31: 0 | J31: 0 | K31: =ประมาณการรายจ่ายกับรายจ่ายจริงแ!B3 -> 110400000 | L31: ประมาณการรายจ่ายกับรายจ่ายจริงแ
A32: 69 | B32: Q2 | D32: 0 | E32: =ประมาณการรายจ่ายกับรายจ่ายจริงแ!A3 -> ศูนย์การเรียนรู้และส่งเสริมสุขภาพสัตว์ภาคเหนือ(NOVEL) | F32: Budget | G32: Expense | H32: Expense Actual | I32: 0 | J32: 0 | K32: =ประมาณการรายจ่ายกับรายจ่ายจริงแ!C3 -> 31034819 | L32: ประมาณการรายจ่ายกับรายจ่ายจริงแ
A33: 69 | B33: Q2 | D33: 0 | E33: =รายรับรายจ่ายกำไร_ย่อย!A4 -> (โรงพยาบาลสัตว์แม่ออน) | F33: Operating | G33: Unit | H33: Revenue | I33: 0 | J33: 0 | K33: =รายรับรายจ่ายกำไร_ย่อย!B4 -> 1762983 | L33: รายรับรายจ่ายกำไร_ย่อย
A34: 69 | B34: Q2 | D34: 0 | E34: =รายรับรายจ่ายกำไร_ย่อย!A4 -> (โรงพยาบาลสัตว์แม่ออน) | F34: Operating | G34: Unit | H34: Expense | I34: 0 | J34: 0 | K34: =รายรับรายจ่ายกำไร_ย่อย!C4 -> 1511583 | L34: รายรับรายจ่ายกำไร_ย่อย
A35: 69 | B35: Q2 | D35: 0 | E35: =รายรับรายจ่ายกำไร_ย่อย!A4 -> (โรงพยาบาลสัตว์แม่ออน) | F35: Operating | G35: Unit | H35: Operating Result | I35: 0 | J35: 0 | K35: =รายรับรายจ่ายกำไร_ย่อย!D4 -> 251400 | L35: รายรับรายจ่ายกำไร_ย่อย
A36: 69 | B36: Q2 | D36: 0 | E36: =ประมาณการรายรับกับรายรับจริง_แย!A4 -> (โรงพยาบาลสัตว์แม่ออน) | F36: Budget | G36: Revenue | H36: Revenue Budget | I36: 0 | J36: 0 | K36: =ประมาณการรายรับกับรายรับจริง_แย!B4 -> 3449600 | L36: ประมาณการรายรับกับรายรับจริง_แย
A37: 69 | B37: Q2 | D37: 0 | E37: =ประมาณการรายรับกับรายรับจริง_แย!A4 -> (โรงพยาบาลสัตว์แม่ออน) | F37: Budget | G37: Revenue | H37: Revenue Actual | I37: 0 | J37: 0 | K37: =ประมาณการรายรับกับรายรับจริง_แย!C4 -> 1762983 | L37: ประมาณการรายรับกับรายรับจริง_แย
A38: 69 | B38: Q2 | D38: 0 | E38: =ประมาณการรายจ่ายกับรายจ่ายจริงแ!A4 -> (โรงพยาบาลสัตว์แม่ออน) | F38: Budget | G38: Expense | H38: Expense Budget | I38: 0 | J38: 0 | K38: =ประมาณการรายจ่ายกับรายจ่ายจริงแ!B4 -> 3200000 | L38: ประมาณการรายจ่ายกับรายจ่ายจริงแ
A39: 69 | B39: Q2 | D39: 0 | E39: =ประมาณการรายจ่ายกับรายจ่ายจริงแ!A4 -> (โรงพยาบาลสัตว์แม่ออน) | F39: Budget | G39: Expense | H39: Expense Actual | I39: 0 | J39: 0 | K39: =ประมาณการรายจ่ายกับรายจ่ายจริงแ!C4 -> 1511583 | L39: ประมาณการรายจ่ายกับรายจ่ายจริงแ
A40: 69 | B40: Q2 | D40: 0 | E40: =รายรับรายจ่ายกำไร_ย่อย!A5 -> โรงพยาบาลสัตว์ใหญ่และปศุสัตว์ | F40: Operating | G40: Unit | H40: Revenue | I40: 0 | J40: 0 | K40: =รายรับรายจ่ายกำไร_ย่อย!B5 -> 1008535 | L40: รายรับรายจ่ายกำไร_ย่อย
A41: 69 | B41: Q2 | D41: 0 | E41: =รายรับรายจ่ายกำไร_ย่อย!A5 -> โรงพยาบาลสัตว์ใหญ่และปศุสัตว์ | F41: Operating | G41: Unit | H41: Expense | I41: 0 | J41: 0 | K41: =รายรับรายจ่ายกำไร_ย่อย!C5 -> 1002935 | L41: รายรับรายจ่ายกำไร_ย่อย
A42: 69 | B42: Q2 | D42: 0 | E42: =รายรับรายจ่ายกำไร_ย่อย!A5 -> โรงพยาบาลสัตว์ใหญ่และปศุสัตว์ | F42: Operating | G42: Unit | H42: Operating Result | I42: 0 | J42: 0 | K42: =รายรับรายจ่ายกำไร_ย่อย!D5 -> 5600 | L42: รายรับรายจ่ายกำไร_ย่อย
A43: 69 | B43: Q2 | D43: 0 | E43: =ประมาณการรายรับกับรายรับจริง_แย!A5 -> โรงพยาบาลสัตว์ใหญ่และปศุสัตว์ | F43: Budget | G43: Revenue | H43: Revenue Budget | I43: 0 | J43: 0 | K43: =ประมาณการรายรับกับรายรับจริง_แย!B5 -> 2176700 | L43: ประมาณการรายรับกับรายรับจริง_แย
A44: 69 | B44: Q2 | D44: 0 | E44: =ประมาณการรายรับกับรายรับจริง_แย!A5 -> โรงพยาบาลสัตว์ใหญ่และปศุสัตว์ | F44: Budget | G44: Revenue | H44: Revenue Actual | I44: 0 | J44: 0 | K44: =ประมาณการรายรับกับรายรับจริง_แย!C5 -> 1008535 | L44: ประมาณการรายรับกับรายรับจริง_แย
A45: 69 | B45: Q2 | D45: 0 | E45: =ประมาณการรายจ่ายกับรายจ่ายจริงแ!A5 -> โรงพยาบาลสัตว์ใหญ่และปศุสัตว์ | F45: Budget | G45: Expense | H45: Expense Budget | I45: 0 | J45: 0 | K45: =ประมาณการรายจ่ายกับรายจ่ายจริงแ!B5 -> 2100000 | L45: ประมาณการรายจ่ายกับรายจ่ายจริงแ
A46: 69 | B46: Q2 | D46: 0 | E46: =ประมาณการรายจ่ายกับรายจ่ายจริงแ!A5 -> โรงพยาบาลสัตว์ใหญ่และปศุสัตว์ | F46: Budget | G46: Expense | H46: Expense Actual | I46: 0 | J46: 0 | K46: =ประมาณการรายจ่ายกับรายจ่ายจริงแ!C5 -> 1002935 | L46: ประมาณการรายจ่ายกับรายจ่ายจริงแ
A47: 69 | B47: Q2 | D47: 0 | E47: =รายรับรายจ่ายกำไร_ย่อย!A6 -> ศูนย์สุขภาพช้างและสัตว์ป่า | F47: Operating | G47: Unit | H47: Revenue | I47: 0 | J47: 0 | K47: =รายรับรายจ่ายกำไร_ย่อย!B6 -> 1044605 | L47: รายรับรายจ่ายกำไร_ย่อย
A48: 69 | B48: Q2 | D48: 0 | E48: =รายรับรายจ่ายกำไร_ย่อย!A6 -> ศูนย์สุขภาพช้างและสัตว์ป่า | F48: Operating | G48: Unit | H48: Expense | I48: 0 | J48: 0 | K48: =รายรับรายจ่ายกำไร_ย่อย!C6 -> 396333 | L48: รายรับรายจ่ายกำไร_ย่อย
A49: 69 | B49: Q2 | D49: 0 | E49: =รายรับรายจ่ายกำไร_ย่อย!A6 -> ศูนย์สุขภาพช้างและสัตว์ป่า | F49: Operating | G49: Unit | H49: Operating Result | I49: 0 | J49: 0 | K49: =รายรับรายจ่ายกำไร_ย่อย!D6 -> 648272 | L49: รายรับรายจ่ายกำไร_ย่อย
A50: 69 | B50: Q2 | D50: 0 | E50: =ประมาณการรายรับกับรายรับจริง_แย!A6 -> ศูนย์สุขภาพช้างและสัตว์ป่า | F50: Budget | G50: Revenue | H50: Revenue Budget | I50: 0 | J50: 0 | K50: =ประมาณการรายรับกับรายรับจริง_แย!B6 -> 2173300 | L50: ประมาณการรายรับกับรายรับจริง_แย
A51: 69 | B51: Q2 | D51: 0 | E51: =ประมาณการรายรับกับรายรับจริง_แย!A6 -> ศูนย์สุขภาพช้างและสัตว์ป่า | F51: Budget | G51: Revenue | H51: Revenue Actual | I51: 0 | J51: 0 | K51: =ประมาณการรายรับกับรายรับจริง_แย!C6 -> 1044605 | L51: ประมาณการรายรับกับรายรับจริง_แย
A52: 69 | B52: Q2 | D52: 0 | E52: =ประมาณการรายจ่ายกับรายจ่ายจริงแ!A6 -> ศูนย์สุขภาพช้างและสัตว์ป่า | F52: Budget | G52: Expense | H52: Expense Budget | I52: 0 | J52: 0 | K52: =ประมาณการรายจ่ายกับรายจ่ายจริงแ!B6 -> 1426100 | L52: ประมาณการรายจ่ายกับรายจ่ายจริงแ
A53: 69 | B53: Q2 | D53: 0 | E53: =ประมาณการรายจ่ายกับรายจ่ายจริงแ!A6 -> ศูนย์สุขภาพช้างและสัตว์ป่า | F53: Budget | G53: Expense | H53: Expense Actual | I53: 0 | J53: 0 | K53: =ประมาณการรายจ่ายกับรายจ่ายจริงแ!C6 -> 396333 | L53: ประมาณการรายจ่ายกับรายจ่ายจริงแ
A54: 69 | B54: Q2 | D54: 0 | E54: =รายรับรายจ่ายกำไร_ย่อย!A7 -> ศูนย์ชันเวชศาสตร์ชันสูตรและนวัตกรรมด้านสุขภาพสัตว์ | F54: Operating | G54: Unit | H54: Revenue | I54: 0 | J54: 0 | K54: =รายรับรายจ่ายกำไร_ย่อย!B7 -> 2741058 | L54: รายรับรายจ่ายกำไร_ย่อย
A55: 69 | B55: Q2 | D55: 0 | E55: =รายรับรายจ่ายกำไร_ย่อย!A7 -> ศูนย์ชันเวชศาสตร์ชันสูตรและนวัตกรรมด้านสุขภาพสัตว์ | F55: Operating | G55: Unit | H55: Expense | I55: 0 | J55: 0 | K55: =รายรับรายจ่ายกำไร_ย่อย!C7 -> 2740822 | L55: รายรับรายจ่ายกำไร_ย่อย
A56: 69 | B56: Q2 | D56: 0 | E56: =รายรับรายจ่ายกำไร_ย่อย!A7 -> ศูนย์ชันเวชศาสตร์ชันสูตรและนวัตกรรมด้านสุขภาพสัตว์ | F56: Operating | G56: Unit | H56: Operating Result | I56: 0 | J56: 0 | K56: =รายรับรายจ่ายกำไร_ย่อย!D7 -> 236 | L56: รายรับรายจ่ายกำไร_ย่อย
A57: 69 | B57: Q2 | D57: 0 | E57: =ประมาณการรายรับกับรายรับจริง_แย!A7 -> ศูนย์ชันเวชศาสตร์ชันสูตรและนวัตกรรมด้านสุขภาพสัตว์ | F57: Budget | G57: Revenue | H57: Revenue Budget | I57: 0 | J57: 0 | K57: =ประมาณการรายรับกับรายรับจริง_แย!B7 -> 7074000 | L57: ประมาณการรายรับกับรายรับจริง_แย
A58: 69 | B58: Q2 | D58: 0 | E58: =ประมาณการรายรับกับรายรับจริง_แย!A7 -> ศูนย์ชันเวชศาสตร์ชันสูตรและนวัตกรรมด้านสุขภาพสัตว์ | F58: Budget | G58: Revenue | H58: Revenue Actual | I58: 0 | J58: 0 | K58: =ประมาณการรายรับกับรายรับจริง_แย!C7 -> 2741058 | L58: ประมาณการรายรับกับรายรับจริง_แย
A59: 69 | B59: Q2 | D59: 0 | E59: =ประมาณการรายจ่ายกับรายจ่ายจริงแ!A7 -> ศูนย์ชันเวชศาสตร์ชันสูตรและนวัตกรรมด้านสุขภาพสัตว์ | F59: Budget | G59: Expense | H59: Expense Budget | I59: 0 | J59: 0 | K59: =ประมาณการรายจ่ายกับรายจ่ายจริงแ!B7 -> 6366600 | L59: ประมาณการรายจ่ายกับรายจ่ายจริงแ
A60: 69 | B60: Q2 | D60: 0 | E60: =ประมาณการรายจ่ายกับรายจ่ายจริงแ!A7 -> ศูนย์ชันเวชศาสตร์ชันสูตรและนวัตกรรมด้านสุขภาพสัตว์ | F60: Budget | G60: Expense | H60: Expense Actual | I60: 0 | J60: 0 | K60: =ประมาณการรายจ่ายกับรายจ่ายจริงแ!C7 -> 2740822 | L60: ประมาณการรายจ่ายกับรายจ่ายจริงแ
A61: 69 | B61: Q2 | D61: 0 | E61: =รายรับรายจ่ายกำไร_ย่อย!A8 -> ศูนย์ความเป็นเลิศด้านเวชศาสตร์แมว | F61: Operating | G61: Unit | H61: Revenue | I61: 0 | J61: 0 | K61: =รายรับรายจ่ายกำไร_ย่อย!B8 -> 0 | L61: รายรับรายจ่ายกำไร_ย่อย
A62: 69 | B62: Q2 | D62: 0 | E62: =รายรับรายจ่ายกำไร_ย่อย!A8 -> ศูนย์ความเป็นเลิศด้านเวชศาสตร์แมว | F62: Operating | G62: Unit | H62: Expense | I62: 0 | J62: 0 | K62: =รายรับรายจ่ายกำไร_ย่อย!C8 -> 0 | L62: รายรับรายจ่ายกำไร_ย่อย
A63: 69 | B63: Q2 | D63: 0 | E63: =รายรับรายจ่ายกำไร_ย่อย!A8 -> ศูนย์ความเป็นเลิศด้านเวชศาสตร์แมว | F63: Operating | G63: Unit | H63: Operating Result | I63: 0 | J63: 0 | K63: =รายรับรายจ่ายกำไร_ย่อย!D8 -> 0 | L63: รายรับรายจ่ายกำไร_ย่อย
A64: 69 | B64: Q2 | D64: 0 | E64: =ประมาณการรายรับกับรายรับจริง_แย!A8 -> ศูนย์ความเป็นเลิศด้านเวชศาสตร์แมว | F64: Budget | G64: Revenue | H64: Revenue Budget | I64: 0 | J64: 0 | K64: =ประมาณการรายรับกับรายรับจริง_แย!B8 -> 0 | L64: ประมาณการรายรับกับรายรับจริง_แย
A65: 69 | B65: Q2 | D65: 0 | E65: =ประมาณการรายรับกับรายรับจริง_แย!A8 -> ศูนย์ความเป็นเลิศด้านเวชศาสตร์แมว | F65: Budget | G65: Revenue | H65: Revenue Actual | I65: 0 | J65: 0 | K65: =ประมาณการรายรับกับรายรับจริง_แย!C8 -> 0 | L65: ประมาณการรายรับกับรายรับจริง_แย
A66: 69 | B66: Q2 | D66: 0 | E66: =ประมาณการรายจ่ายกับรายจ่ายจริงแ!A8 -> ศูนย์ความเป็นเลิศด้านเวชศาสตร์แมว | F66: Budget | G66: Expense | H66: Expense Budget | I66: 0 | J66: 0 | K66: =ประมาณการรายจ่ายกับรายจ่ายจริงแ!B8 -> 0 | L66: ประมาณการรายจ่ายกับรายจ่ายจริงแ
A67: 69 | B67: Q2 | D67: 0 | E67: =ประมาณการรายจ่ายกับรายจ่ายจริงแ!A8 -> ศูนย์ความเป็นเลิศด้านเวชศาสตร์แมว | F67: Budget | G67: Expense | H67: Expense Actual | I67: 0 | J67: 0 | K67: =ประมาณการรายจ่ายกับรายจ่ายจริงแ!C8 -> 0 | L67: ประมาณการรายจ่ายกับรายจ่ายจริงแ
A68: 69 | B68: Q2 | D68: 0 | E68: =รายรับรายจ่ายกำไร_ย่อย!A9 -> Pet CMU (กลุ่มงานบ่มเพาะวิสาหกิจทางสัตวแพทย์) | F68: Operating | G68: Unit | H68: Revenue | I68: 0 | J68: 0 | K68: =รายรับรายจ่ายกำไร_ย่อย!B9 -> 7351957 | L68: รายรับรายจ่ายกำไร_ย่อย
A69: 69 | B69: Q2 | D69: 0 | E69: =รายรับรายจ่ายกำไร_ย่อย!A9 -> Pet CMU (กลุ่มงานบ่มเพาะวิสาหกิจทางสัตวแพทย์) | F69: Operating | G69: Unit | H69: Expense | I69: 0 | J69: 0 | K69: =รายรับรายจ่ายกำไร_ย่อย!C9 -> 4155836 | L69: รายรับรายจ่ายกำไร_ย่อย
A70: 69 | B70: Q2 | D70: 0 | E70: =รายรับรายจ่ายกำไร_ย่อย!A9 -> Pet CMU (กลุ่มงานบ่มเพาะวิสาหกิจทางสัตวแพทย์) | F70: Operating | G70: Unit | H70: Operating Result | I70: 0 | J70: 0 | K70: =รายรับรายจ่ายกำไร_ย่อย!D9 -> 3196121 | L70: รายรับรายจ่ายกำไร_ย่อย
A71: 69 | B71: Q2 | D71: 0 | E71: =ประมาณการรายรับกับรายรับจริง_แย!A9 -> Pet CMU (กลุ่มงานบ่มเพาะวิสาหกิจทางสัตวแพทย์) | F71: Budget | G71: Revenue | H71: Revenue Budget | I71: 0 | J71: 0 | K71: =ประมาณการรายรับกับรายรับจริง_แย!B9 -> 7959800 | L71: ประมาณการรายรับกับรายรับจริง_แย
A72: 69 | B72: Q2 | D72: 0 | E72: =ประมาณการรายรับกับรายรับจริง_แย!A9 -> Pet CMU (กลุ่มงานบ่มเพาะวิสาหกิจทางสัตวแพทย์) | F72: Budget | G72: Revenue | H72: Revenue Actual | I72: 0 | J72: 0 | K72: =ประมาณการรายรับกับรายรับจริง_แย!C9 -> 7351957 | L72: ประมาณการรายรับกับรายรับจริง_แย
A73: 69 | B73: Q2 | D73: 0 | E73: =ประมาณการรายจ่ายกับรายจ่ายจริงแ!A9 -> Pet CMU (กลุ่มงานบ่มเพาะวิสาหกิจทางสัตวแพทย์) | F73: Budget | G73: Expense | H73: Expense Budget | I73: 0 | J73: 0 | K73: =ประมาณการรายจ่ายกับรายจ่ายจริงแ!B9 -> 7163800 | L73: ประมาณการรายจ่ายกับรายจ่ายจริงแ
A74: 69 | B74: Q2 | D74: 0 | E74: =ประมาณการรายจ่ายกับรายจ่ายจริงแ!A9 -> Pet CMU (กลุ่มงานบ่มเพาะวิสาหกิจทางสัตวแพทย์) | F74: Budget | G74: Expense | H74: Expense Actual | I74: 0 | J74: 0 | K74: =ประมาณการรายจ่ายกับรายจ่ายจริงแ!C9 -> 4155836 | L74: ประมาณการรายจ่ายกับรายจ่ายจริงแ
A75: 69 | B75: Q2 | D75: 0 | E75: =รายรับรายจ่ายกำไร_ย่อย!A10 -> ศูนย์สัตวแพทย์สาธารณสุขและอาหารปลอดภัยเอเชียแปซิฟิก | F75: Operating | G75: Unit | H75: Revenue | I75: 0 | J75: 0 | K75: =รายรับรายจ่ายกำไร_ย่อย!B10 -> 11985 | L75: รายรับรายจ่ายกำไร_ย่อย
A76: 69 | B76: Q2 | D76: 0 | E76: =รายรับรายจ่ายกำไร_ย่อย!A10 -> ศูนย์สัตวแพทย์สาธารณสุขและอาหารปลอดภัยเอเชียแปซิฟิก | F76: Operating | G76: Unit | H76: Expense | I76: 0 | J76: 0 | K76: =รายรับรายจ่ายกำไร_ย่อย!C10 -> 189641 | L76: รายรับรายจ่ายกำไร_ย่อย
A77: 69 | B77: Q2 | D77: 0 | E77: =รายรับรายจ่ายกำไร_ย่อย!A10 -> ศูนย์สัตวแพทย์สาธารณสุขและอาหารปลอดภัยเอเชียแปซิฟิก | F77: Operating | G77: Unit | H77: Operating Result | I77: 0 | J77: 0 | K77: =รายรับรายจ่ายกำไร_ย่อย!D10 -> -177656 | L77: รายรับรายจ่ายกำไร_ย่อย
A78: 69 | B78: Q2 | D78: 0 | E78: =ประมาณการรายรับกับรายรับจริง_แย!A10 -> ศูนย์สัตวแพทย์สาธารณสุขและอาหารปลอดภัยเอเชียแปซิฟิก | F78: Budget | G78: Revenue | H78: Revenue Budget | I78: 0 | J78: 0 | K78: =ประมาณการรายรับกับรายรับจริง_แย!B10 -> 526500 | L78: ประมาณการรายรับกับรายรับจริง_แย
A79: 69 | B79: Q2 | D79: 0 | E79: =ประมาณการรายรับกับรายรับจริง_แย!A10 -> ศูนย์สัตวแพทย์สาธารณสุขและอาหารปลอดภัยเอเชียแปซิฟิก | F79: Budget | G79: Revenue | H79: Revenue Actual | I79: 0 | J79: 0 | K79: =ประมาณการรายรับกับรายรับจริง_แย!C10 -> 11985 | L79: ประมาณการรายรับกับรายรับจริง_แย
A80: 69 | B80: Q2 | D80: 0 | E80: =ประมาณการรายจ่ายกับรายจ่ายจริงแ!A10 -> ศูนย์สัตวแพทย์สาธารณสุขและอาหารปลอดภัยเอเชียแปซิฟิก | F80: Budget | G80: Expense | H80: Expense Budget | I80: 0 | J80: 0 | K80: =ประมาณการรายจ่ายกับรายจ่ายจริงแ!B10 -> 500000 | L80: ประมาณการรายจ่ายกับรายจ่ายจริงแ
A81: 69 | B81: Q2 | D81: 0 | E81: =ประมาณการรายจ่ายกับรายจ่ายจริงแ!A10 -> ศูนย์สัตวแพทย์สาธารณสุขและอาหารปลอดภัยเอเชียแปซิฟิก | F81: Budget | G81: Expense | H81: Expense Actual | I81: 0 | J81: 0 | K81: =ประมาณการรายจ่ายกับรายจ่ายจริงแ!C10 -> 189641 | L81: ประมาณการรายจ่ายกับรายจ่ายจริงแ
A82: 69 | B82: Q2 | D82: 0 | E82: =รายรับรายจ่ายกำไร_ย่อย!A11 -> ศูนย์เฝ้าระวังสุขภาพหนึ่งเดียว PODD | F82: Operating | G82: Unit | H82: Revenue | I82: 0 | J82: 0 | K82: =รายรับรายจ่ายกำไร_ย่อย!B11 -> 1029558 | L82: รายรับรายจ่ายกำไร_ย่อย
A83: 69 | B83: Q2 | D83: 0 | E83: =รายรับรายจ่ายกำไร_ย่อย!A11 -> ศูนย์เฝ้าระวังสุขภาพหนึ่งเดียว PODD | F83: Operating | G83: Unit | H83: Expense | I83: 0 | J83: 0 | K83: =รายรับรายจ่ายกำไร_ย่อย!C11 -> 2307358 | L83: รายรับรายจ่ายกำไร_ย่อย
A84: 69 | B84: Q2 | D84: 0 | E84: =รายรับรายจ่ายกำไร_ย่อย!A11 -> ศูนย์เฝ้าระวังสุขภาพหนึ่งเดียว PODD | F84: Operating | G84: Unit | H84: Operating Result | I84: 0 | J84: 0 | K84: =รายรับรายจ่ายกำไร_ย่อย!D11 -> -1277800 | L84: รายรับรายจ่ายกำไร_ย่อย
A85: 69 | B85: Q2 | D85: 0 | E85: =ประมาณการรายรับกับรายรับจริง_แย!A11 -> ศูนย์เฝ้าระวังสุขภาพหนึ่งเดียว PODD | F85: Budget | G85: Revenue | H85: Revenue Budget | I85: 0 | J85: 0 | K85: =ประมาณการรายรับกับรายรับจริง_แย!B11 -> 4200000 | L85: ประมาณการรายรับกับรายรับจริง_แย
A86: 69 | B86: Q2 | D86: 0 | E86: =ประมาณการรายรับกับรายรับจริง_แย!A11 -> ศูนย์เฝ้าระวังสุขภาพหนึ่งเดียว PODD | F86: Budget | G86: Revenue | H86: Revenue Actual | I86: 0 | J86: 0 | K86: =ประมาณการรายรับกับรายรับจริง_แย!C11 -> 1029558 | L86: ประมาณการรายรับกับรายรับจริง_แย
A87: 69 | B87: Q2 | D87: 0 | E87: =ประมาณการรายจ่ายกับรายจ่ายจริงแ!A11 -> ศูนย์เฝ้าระวังสุขภาพหนึ่งเดียว PODD | F87: Budget | G87: Expense | H87: Expense Budget | I87: 0 | J87: 0 | K87: =ประมาณการรายจ่ายกับรายจ่ายจริงแ!B11 -> 4000000 | L87: ประมาณการรายจ่ายกับรายจ่ายจริงแ
A88: 69 | B88: Q2 | D88: 0 | E88: =ประมาณการรายจ่ายกับรายจ่ายจริงแ!A11 -> ศูนย์เฝ้าระวังสุขภาพหนึ่งเดียว PODD | F88: Budget | G88: Expense | H88: Expense Actual | I88: 0 | J88: 0 | K88: =ประมาณการรายจ่ายกับรายจ่ายจริงแ!C11 -> 2307358 | L88: ประมาณการรายจ่ายกับรายจ่ายจริงแ
A89: 69 | B89: Q2 | D89: 0 | E89: =รายรับรายจ่ายกำไร_ย่อย!A12 -> สำนักงานโรงพยาบาลสัตว์(ศรีบัวบาน) | F89: Operating | G89: Unit | H89: Revenue | I89: 0 | J89: 0 | K89: =รายรับรายจ่ายกำไร_ย่อย!B12 -> 0 | L89: รายรับรายจ่ายกำไร_ย่อย
A90: 69 | B90: Q2 | D90: 0 | E90: =รายรับรายจ่ายกำไร_ย่อย!A12 -> สำนักงานโรงพยาบาลสัตว์(ศรีบัวบาน) | F90: Operating | G90: Unit | H90: Expense | I90: 0 | J90: 0 | K90: =รายรับรายจ่ายกำไร_ย่อย!C12 -> 0 | L90: รายรับรายจ่ายกำไร_ย่อย
A91: 69 | B91: Q2 | D91: 0 | E91: =รายรับรายจ่ายกำไร_ย่อย!A12 -> สำนักงานโรงพยาบาลสัตว์(ศรีบัวบาน) | F91: Operating | G91: Unit | H91: Operating Result | I91: 0 | J91: 0 | K91: =รายรับรายจ่ายกำไร_ย่อย!D12 -> 0 | L91: รายรับรายจ่ายกำไร_ย่อย
A92: 69 | B92: Q2 | D92: 0 | E92: =ประมาณการรายรับกับรายรับจริง_แย!A12 -> สำนักงานโรงพยาบาลสัตว์(ศรีบัวบาน) | F92: Budget | G92: Revenue | H92: Revenue Budget | I92: 0 | J92: 0 | K92: =ประมาณการรายรับกับรายรับจริง_แย!B12 -> 700000 | L92: ประมาณการรายรับกับรายรับจริง_แย
A93: 69 | B93: Q2 | D93: 0 | E93: =ประมาณการรายรับกับรายรับจริง_แย!A12 -> สำนักงานโรงพยาบาลสัตว์(ศรีบัวบาน) | F93: Budget | G93: Revenue | H93: Revenue Actual | I93: 0 | J93: 0 | K93: =ประมาณการรายรับกับรายรับจริง_แย!C12 -> 0 | L93: ประมาณการรายรับกับรายรับจริง_แย
A94: 69 | B94: Q2 | D94: 0 | E94: =ประมาณการรายจ่ายกับรายจ่ายจริงแ!A12 -> สำนักงานโรงพยาบาลสัตว์(ศรีบัวบาน) | F94: Budget | G94: Expense | H94: Expense Budget | I94: 0 | J94: 0 | K94: =ประมาณการรายจ่ายกับรายจ่ายจริงแ!B12 -> 500000 | L94: ประมาณการรายจ่ายกับรายจ่ายจริงแ
A95: 69 | B95: Q2 | D95: 0 | E95: =ประมาณการรายจ่ายกับรายจ่ายจริงแ!A12 -> สำนักงานโรงพยาบาลสัตว์(ศรีบัวบาน) | F95: Budget | G95: Expense | H95: Expense Actual | I95: 0 | J95: 0 | K95: =ประมาณการรายจ่ายกับรายจ่ายจริงแ!C12 -> 0 | L95: ประมาณการรายจ่ายกับรายจ่ายจริงแ
A96: 69 | B96: Q2 | D96: 0 | E96: ทั้งหมด | F96: Government Budget | G96: Total | H96: Government Budget | I96: 0 | J96: 0 | K96: =งบประมาณแผ่นดิน!B2 -> 207098179 | L96: งบประมาณแผ่นดิน
A97: 69 | B97: Q2 | D97: 0 | E97: ทั้งหมด | F97: Government Budget | G97: Total | H97: Government Actual | I97: 0 | J97: 0 | K97: =งบประมาณแผ่นดิน!C2 -> 89248624 | L97: งบประมาณแผ่นดิน

Sheet Dashboard_Data
A1: Dashboard_Data — Formula-Driven KPI and Chart Helper | B1: Dashboard_Data — Formula-Driven KPI and Chart Helper | C1: Dashboard_Data — Formula-Driven KPI and Chart Helper | D1: Dashboard_Data — Formula-Driven KPI and Chart Helper | E1: Dashboard_Data — Formula-Driven KPI and Chart Helper | F1: Dashboard_Data — Formula-Driven KPI and Chart Helper | G1: Dashboard_Data — Formula-Driven KPI and Chart Helper | H1: Dashboard_Data — Formula-Driven KPI and Chart Helper | I1: Dashboard_Data — Formula-Driven KPI and Chart Helper | J1: Dashboard_Data — Formula-Driven KPI and Chart Helper
A3: KPI | B3: Value | D3: Period | E3: Revenue | F3: Expense | G3: Operating Result | I3: Budget vs Actual | J3: Budget | K3: Actual
A4: Total Revenue | B4: =IFERROR(SUMIFS(Data_Clean!$K$3:$K$1000,Data_Clean!$H$3:$H$1000,"Revenue",Data_Clean!$A$3:$A$1000,Config!$B$4,Data_Clean!$B$3:$B$1000,Config!$B$5,Data_Clean!$E$3:$E$1000,Config!$B$6),0) -> 73281544 | D4: Q3/68 | E4: =รายรับรายจ่ายกำไร!B5 -> 90260853 | F4: =รายรับรายจ่ายกำไร!C5 -> 84229576 | G4: =รายรับรายจ่ายกำไร!D5 -> 6031277 | I4: Revenue | J4: =ประมาณการรายรับกับรายรับจริง_รว!B2 -> 171825100 | K4: =ประมาณการรายรับกับรายรับจริง_รว!C2 -> 73281544
A5: Total Expense | B5: =IFERROR(SUMIFS(Data_Clean!$K$3:$K$1000,Data_Clean!$H$3:$H$1000,"Expense",Data_Clean!$A$3:$A$1000,Config!$B$4,Data_Clean!$B$3:$B$1000,Config!$B$5,Data_Clean!$E$3:$E$1000,Config!$B$6),0) -> 57694327 | D5: Q4/68 | E5: =รายรับรายจ่ายกำไร!B4 -> 131408229 | F5: =รายรับรายจ่ายกำไร!C4 -> 127865373 | G5: =รายรับรายจ่ายกำไร!D4 -> 3542856 | I5: Expense | J5: =ประมาณการรายจ่ายกับรายจ่ายจริงร!B2 -> 165565500 | K5: =ประมาณการรายจ่ายกับรายจ่ายจริงร!C2 -> 57694327
A6: Operating Result | B6: =B4-B5 -> 15587217 | D6: Q1/69 | E6: =รายรับรายจ่ายกำไร!B3 -> 46683658 | F6: =รายรับรายจ่ายกำไร!C3 -> 51712260 | G6: =รายรับรายจ่ายกำไร!D3 -> -5028602
A7: Operating Margin | B7: =IFERROR(B6/B4,0) -> 0.21270317 | D7: Q2/69 | E7: =รายรับรายจ่ายกำไร!B2 -> 73281544 | F7: =รายรับรายจ่ายกำไร!C2 -> 57694327 | G7: =รายรับรายจ่ายกำไร!D2 -> 15587217
A8: Expense-to-Revenue Ratio | B8: =IFERROR(B5/B4,0) -> 0.78729683
A9: Financial Liquidity | B9: =IFERROR(SUMIFS(Data_Clean!$K$3:$K$1000,Data_Clean!$H$3:$H$1000,"Liquidity",Data_Clean!$A$3:$A$1000,Config!$B$4,Data_Clean!$B$3:$B$1000,Config!$B$5),0) -> 0.35268405
A10: Revenue Budget | B10: =IFERROR(SUMIFS(Data_Clean!$K$3:$K$1000,Data_Clean!$H$3:$H$1000,"Revenue Budget",Data_Clean!$A$3:$A$1000,Config!$B$4,Data_Clean!$B$3:$B$1000,Config!$B$5),0) -> 171677900
A11: Revenue Actual | B11: =IFERROR(SUMIFS(Data_Clean!$K$3:$K$1000,Data_Clean!$H$3:$H$1000,"Revenue Actual",Data_Clean!$A$3:$A$1000,Config!$B$4,Data_Clean!$B$3:$B$1000,Config!$B$5),0) -> 73281076
A12: Revenue Achievement | B12: =IFERROR(B11/B10,0) -> 0.42685212
A13: Expense Budget | B13: =IFERROR(SUMIFS(Data_Clean!$K$3:$K$1000,Data_Clean!$H$3:$H$1000,"Expense Budget",Data_Clean!$A$3:$A$1000,Config!$B$4,Data_Clean!$B$3:$B$1000,Config!$B$5),0) -> 165295300
A14: Expense Actual | B14: =IFERROR(SUMIFS(Data_Clean!$K$3:$K$1000,Data_Clean!$H$3:$H$1000,"Expense Actual",Data_Clean!$A$3:$A$1000,Config!$B$4,Data_Clean!$B$3:$B$1000,Config!$B$5),0) -> 57694326
A15: Expense Utilization | B15: =IFERROR(B14/B13,0) -> 0.34903791
A16: Government Budget Utilization | B16: =IFERROR(SUMIFS(Data_Clean!$K$3:$K$1000,Data_Clean!$H$3:$H$1000,"Government Actual",Data_Clean!$A$3:$A$1000,Config!$B$4,Data_Clean!$B$3:$B$1000,Config!$B$5)/SUMIFS(Data_Clean!$K$3:$K$1000,Data_Clean!$H$3:$H$1000,"Government Budget",Data_Clean!$A$3:$A$1000,Config!$B$4,Data_Clean!$B$3:$B$1000,Config!$B$5),0) -> 0.43094838

Sheet Config
A1: Configuration & Interactive Filters | B1: Configuration & Interactive Filters | C1: Configuration & Interactive Filters | D1: Configuration & Interactive Filters | E1: Configuration & Interactive Filters | F1: Configuration & Interactive Filters
A3: Filter / setting | B3: Selected value | D3: Available fiscal years | E3: Available quarters
A4: Fiscal Year | B4: 69 | D4: 68 | E4: Q1
A5: Quarter | B5: Q2 | D5: 69 | E5: Q2
A6: Unit | B6: ทั้งหมด | E6: Q3
A7: Refresh Date | B7: 46216 | D7: Notes | E7: Q4
A8: Liquidity watch threshold — PLACEHOLDER (management to approve) | B8: 0.4
A9: Liquidity good threshold — PLACEHOLDER (management to approve) | B9: 0.5 | D9: How to use
A10: Revenue achievement target — PLACEHOLDER (management to approve) | B10: 0.9 | D10: Change B4:B6 to update formula-driven KPIs and tables.
A11: Expense utilization target — PLACEHOLDER (management to approve) | B11: 0.85 | D11: Use Excel table filters in Data_Clean for detailed analysis.
D12: Thresholds are management placeholders and may be edited.

Sheet README
A1: README — Vet CMU Interactive Financial Dashboard | B1: README — Vet CMU Interactive Financial Dashboard | C1: README — Vet CMU Interactive Financial Dashboard | D1: README — Vet CMU Interactive Financial Dashboard | E1: README — Vet CMU Interactive Financial Dashboard | F1: README — Vet CMU Interactive Financial Dashboard
A3: Topic | B3: Description
A4: Purpose | B4: Executive financial monitoring using the actual workbook structure identified in Data_Audit.
A5: Source preservation | B5: All 10 original source sheets are retained. No original source formula or raw data was changed.
A6: KPI data | B6: All displayed KPI amounts and percentages are formula-linked to actual values in original sheets via Data_Clean and Dashboard_Data. No illustrative or sample KPI values are used.
A7: Periods available | B7: Quarterly operating data: Q3/68 through Q2/69. Unit, budget, and government-budget data: Q2/69 snapshot.
A8: Filters | B8: Use Config!B4:B6 dropdowns for Fiscal Year, Quarter, and Unit. The Dashboard and helper formulas update from those selections where the source provides the dimension.
A9: Placeholder inputs | B9: ONLY Config!B8:B11 are placeholders: liquidity and budget performance thresholds. They are clearly labeled “PLACEHOLDER (management to approve)” and may be revised by management.
A10: Formula controls | B10: All new ratios use IFERROR to avoid calculation errors. Source-sheet #NAME? results are preserved and documented in Data_Audit; dashboard formulas use the underlying actual/budget values instead.
A11: Refresh process | B11: Append or update formula-linked rows in Data_Clean from the retained original sheets, then extend the Excel Table and refresh the Dashboard_Data formulas as required.

Sheet Financial_Analysis
A1: Financial Analysis — Quarterly and Budget Review | B1: Financial Analysis — Quarterly and Budget Review | C1: Financial Analysis — Quarterly and Budget Review | D1: Financial Analysis — Quarterly and Budget Review | E1: Financial Analysis — Quarterly and Budget Review | F1: Financial Analysis — Quarterly and Budget Review | G1: Financial Analysis — Quarterly and Budget Review | H1: Financial Analysis — Quarterly and Budget Review | I1: Financial Analysis — Quarterly and Budget Review | J1: Financial Analysis — Quarterly and Budget Review
A3: Quarterly Operating Summary | B3: Quarterly Operating Summary | C3: Quarterly Operating Summary | D3: Quarterly Operating Summary | E3: Quarterly Operating Summary | F3: Quarterly Operating Summary | H3: Budget Variance | I3: Budget Variance | J3: Budget Variance
A4: =Dashboard_Data!D3 -> Period | B4: =Dashboard_Data!E3 -> Revenue | C4: =Dashboard_Data!F3 -> Expense | D4: =Dashboard_Data!G3 -> Operating Result | E4: ="Operating Margin" -> Operating Margin | F4: ="Expense/Revenue" -> Expense/Revenue | H4: Metric | I4: Variance | J4: Status
A5: =Dashboard_Data!D4 -> Q3/68 | B5: =Dashboard_Data!E4 -> 90260853 | C5: =Dashboard_Data!F4 -> 84229576 | D5: =Dashboard_Data!G4 -> 6031277 | E5: =IFERROR(D5/B5,0) -> 0.066820519 | F5: =IFERROR(C5/B5,0) -> 0.93317948 | H5: Revenue | I5: =Dashboard_Data!B11-Dashboard_Data!B10 -> -98396824 | J5: =IF(I5>=0,"Above plan","Below plan") -> Below plan
A6: =Dashboard_Data!D5 -> Q4/68 | B6: =Dashboard_Data!E5 -> 131408229 | C6: =Dashboard_Data!F5 -> 127865373 | D6: =Dashboard_Data!G5 -> 3542856 | E6: =IFERROR(D6/B6,0) -> 0.026960686 | F6: =IFERROR(C6/B6,0) -> 0.97303931 | H6: Expense | I6: =Dashboard_Data!B13-Dashboard_Data!B14 -> 107600974 | J6: =IF(I6>=0,"Within plan","Over plan") -> Within plan
A7: =Dashboard_Data!D6 -> Q1/69 | B7: =Dashboard_Data!E6 -> 46683658 | C7: =Dashboard_Data!F6 -> 51712260 | D7: =Dashboard_Data!G6 -> -5028602 | E7: =IFERROR(D7/B7,0) -> -0.10771654 | F7: =IFERROR(C7/B7,0) -> 1.1077165
A8: =Dashboard_Data!D7 -> Q2/69 | B8: =Dashboard_Data!E7 -> 73281544 | C8: =Dashboard_Data!F7 -> 57694327 | D8: =Dashboard_Data!G7 -> 15587217 | E8: =IFERROR(D8/B8,0) -> 0.21270317 | F8: =IFERROR(C8/B8,0) -> 0.78729683
A11: Unit Budget Achievement | B11: Unit Budget Achievement | C11: Unit Budget Achievement | D11: Unit Budget Achievement | E11: Unit Budget Achievement | F11: Unit Budget Achievement
A12: =ประมาณการรายรับกับรายรับจริง_แย!A1 -> Sub-unit (A) | B12: =ประมาณการรายรับกับรายรับจริง_แย!B1 -> Budgeted Revenue | C12: =ประมาณการรายรับกับรายรับจริง_แย!C1 -> Revenue Q2 | D12: =ประมาณการรายรับกับรายรับจริง_แย!D1 -> Percentage(%) | E12: ="Expense Budget" -> Expense Budget | F12: ="Expense Actual" -> Expense Actual
A13: =ประมาณการรายรับกับรายรับจริง_แย!A2 -> สำนักงาน คณะสัตวแพทยศาสตร์ | B13: =ประมาณการรายรับกับรายรับจริง_แย!B2 -> 28518000 | C13: =ประมาณการรายรับกับรายรับจริง_แย!C2 -> 18542474 | D13: =ประมาณการรายรับกับรายรับจริง_แย!D2 -> 0.65020247 | E13: =ประมาณการรายจ่ายกับรายจ่ายจริงแ!B2 -> 29638800 | F13: =ประมาณการรายจ่ายกับรายจ่ายจริงแ!C2 -> 14354999
A14: =ประมาณการรายรับกับรายรับจริง_แย!A3 -> ศูนย์การเรียนรู้และส่งเสริมสุขภาพสัตว์ภาคเหนือ(NOVEL) | B14: =ประมาณการรายรับกับรายรับจริง_แย!B3 -> 114900000 | C14: =ประมาณการรายรับกับรายรับจริง_แย!C3 -> 39787921 | D14: =ประมาณการรายรับกับรายรับจริง_แย!D3 -> 0.34628304 | E14: =ประมาณการรายจ่ายกับรายจ่ายจริงแ!B3 -> 110400000 | F14: =ประมาณการรายจ่ายกับรายจ่ายจริงแ!C3 -> 31034819
A15: =ประมาณการรายรับกับรายรับจริง_แย!A4 -> (โรงพยาบาลสัตว์แม่ออน) | B15: =ประมาณการรายรับกับรายรับจริง_แย!B4 -> 3449600 | C15: =ประมาณการรายรับกับรายรับจริง_แย!C4 -> 1762983 | D15: =ประมาณการรายรับกับรายรับจริง_แย!D4 -> 0.51106882 | E15: =ประมาณการรายจ่ายกับรายจ่ายจริงแ!B4 -> 3200000 | F15: =ประมาณการรายจ่ายกับรายจ่ายจริงแ!C4 -> 1511583
A16: =ประมาณการรายรับกับรายรับจริง_แย!A5 -> โรงพยาบาลสัตว์ใหญ่และปศุสัตว์ | B16: =ประมาณการรายรับกับรายรับจริง_แย!B5 -> 2176700 | C16: =ประมาณการรายรับกับรายรับจริง_แย!C5 -> 1008535 | D16: =ประมาณการรายรับกับรายรับจริง_แย!D5 -> 0.46333211 | E16: =ประมาณการรายจ่ายกับรายจ่ายจริงแ!B5 -> 2100000 | F16: =ประมาณการรายจ่ายกับรายจ่ายจริงแ!C5 -> 1002935
A17: =ประมาณการรายรับกับรายรับจริง_แย!A6 -> ศูนย์สุขภาพช้างและสัตว์ป่า | B17: =ประมาณการรายรับกับรายรับจริง_แย!B6 -> 2173300 | C17: =ประมาณการรายรับกับรายรับจริง_แย!C6 -> 1044605 | D17: =ประมาณการรายรับกับรายรับจริง_แย!D6 -> 0.48065384 | E17: =ประมาณการรายจ่ายกับรายจ่ายจริงแ!B6 -> 1426100 | F17: =ประมาณการรายจ่ายกับรายจ่ายจริงแ!C6 -> 396333
A18: =ประมาณการรายรับกับรายรับจริง_แย!A7 -> ศูนย์ชันเวชศาสตร์ชันสูตรและนวัตกรรมด้านสุขภาพสัตว์ | B18: =ประมาณการรายรับกับรายรับจริง_แย!B7 -> 7074000 | C18: =ประมาณการรายรับกับรายรับจริง_แย!C7 -> 2741058 | D18: =ประมาณการรายรับกับรายรับจริง_แย!D7 -> 0.38748346 | E18: =ประมาณการรายจ่ายกับรายจ่ายจริงแ!B7 -> 6366600 | F18: =ประมาณการรายจ่ายกับรายจ่ายจริงแ!C7 -> 2740822
A19: =ประมาณการรายรับกับรายรับจริง_แย!A8 -> ศูนย์ความเป็นเลิศด้านเวชศาสตร์แมว | B19: =ประมาณการรายรับกับรายรับจริง_แย!B8 -> 0 | C19: =ประมาณการรายรับกับรายรับจริง_แย!C8 -> 0 | D19: =ประมาณการรายรับกับรายรับจริง_แย!D8 -> 0 | E19: =ประมาณการรายจ่ายกับรายจ่ายจริงแ!B8 -> 0 | F19: =ประมาณการรายจ่ายกับรายจ่ายจริงแ!C8 -> 0
A20: =ประมาณการรายรับกับรายรับจริง_แย!A9 -> Pet CMU (กลุ่มงานบ่มเพาะวิสาหกิจทางสัตวแพทย์) | B20: =ประมาณการรายรับกับรายรับจริง_แย!B9 -> 7959800 | C20: =ประมาณการรายรับกับรายรับจริง_แย!C9 -> 7351957 | D20: =ประมาณการรายรับกับรายรับจริง_แย!D9 -> 0.9236359 | E20: =ประมาณการรายจ่ายกับรายจ่ายจริงแ!B9 -> 7163800 | F20: =ประมาณการรายจ่ายกับรายจ่ายจริงแ!C9 -> 4155836
A21: =ประมาณการรายรับกับรายรับจริง_แย!A10 -> ศูนย์สัตวแพทย์สาธารณสุขและอาหารปลอดภัยเอเชียแปซิฟิก | B21: =ประมาณการรายรับกับรายรับจริง_แย!B10 -> 526500 | C21: =ประมาณการรายรับกับรายรับจริง_แย!C10 -> 11985 | D21: =ประมาณการรายรับกับรายรับจริง_แย!D10 -> 0.022763533 | E21: =ประมาณการรายจ่ายกับรายจ่ายจริงแ!B10 -> 500000 | F21: =ประมาณการรายจ่ายกับรายจ่ายจริงแ!C10 -> 189641
A22: =ประมาณการรายรับกับรายรับจริง_แย!A11 -> ศูนย์เฝ้าระวังสุขภาพหนึ่งเดียว PODD | B22: =ประมาณการรายรับกับรายรับจริง_แย!B11 -> 4200000 | C22: =ประมาณการรายรับกับรายรับจริง_แย!C11 -> 1029558 | D22: =ประมาณการรายรับกับรายรับจริง_แย!D11 -> 0.24513286 | E22: =ประมาณการรายจ่ายกับรายจ่ายจริงแ!B11 -> 4000000 | F22: =ประมาณการรายจ่ายกับรายจ่ายจริงแ!C11 -> 2307358
A23: =ประมาณการรายรับกับรายรับจริง_แย!A12 -> สำนักงานโรงพยาบาลสัตว์(ศรีบัวบาน) | B23: =ประมาณการรายรับกับรายรับจริง_แย!B12 -> 700000 | C23: =ประมาณการรายรับกับรายรับจริง_แย!C12 -> 0 | D23: =ประมาณการรายรับกับรายรับจริง_แย!D12 -> 0 | E23: =ประมาณการรายจ่ายกับรายจ่ายจริงแ!B12 -> 500000 | F23: =ประมาณการรายจ่ายกับรายจ่ายจริงแ!C12 -> 0

Sheet Unit_Performance
A1: Unit Performance — Q2/69 | B1: Unit Performance — Q2/69 | C1: Unit Performance — Q2/69 | D1: Unit Performance — Q2/69 | E1: Unit Performance — Q2/69 | F1: Unit Performance — Q2/69 | G1: Unit Performance — Q2/69 | H1: Unit Performance — Q2/69
A3: Unit | B3: Revenue | C3: Expense | D3: Operating Result | E3: Margin | F3: Revenue Budget | G3: Revenue Achievement | H3: Expense Utilization
A4: =รายรับรายจ่ายกำไร_ย่อย!A2 -> สำนักงาน คณะสัตวแพทยศาสตร์ | B4: =รายรับรายจ่ายกำไร_ย่อย!B2 -> 18542474 | C4: =รายรับรายจ่ายกำไร_ย่อย!C2 -> 14354999 | D4: =รายรับรายจ่ายกำไร_ย่อย!D2 -> 4187475 | E4: =IFERROR(D4/B4,0) -> 0.22583152 | F4: =ประมาณการรายรับกับรายรับจริง_แย!B2 -> 28518000 | G4: =IFERROR(B4/F4,0) -> 0.65020247 | H4: =IFERROR(C4/ประมาณการรายจ่ายกับรายจ่ายจริงแ!B2,0) -> 0.48433132
A5: =รายรับรายจ่ายกำไร_ย่อย!A3 -> ศูนย์การเรียนรู้และส่งเสริมสุขภาพสัตว์ภาคเหนือ(NOVEL) | B5: =รายรับรายจ่ายกำไร_ย่อย!B3 -> 39787921 | C5: =รายรับรายจ่ายกำไร_ย่อย!C3 -> 31034819 | D5: =รายรับรายจ่ายกำไร_ย่อย!D3 -> 8753102 | E5: =IFERROR(D5/B5,0) -> 0.21999395 | F5: =ประมาณการรายรับกับรายรับจริง_แย!B3 -> 114900000 | G5: =IFERROR(B5/F5,0) -> 0.34628304 | H5: =IFERROR(C5/ประมาณการรายจ่ายกับรายจ่ายจริงแ!B3,0) -> 0.28111249
A6: =รายรับรายจ่ายกำไร_ย่อย!A4 -> (โรงพยาบาลสัตว์แม่ออน) | B6: =รายรับรายจ่ายกำไร_ย่อย!B4 -> 1762983 | C6: =รายรับรายจ่ายกำไร_ย่อย!C4 -> 1511583 | D6: =รายรับรายจ่ายกำไร_ย่อย!D4 -> 251400 | E6: =IFERROR(D6/B6,0) -> 0.14259922 | F6: =ประมาณการรายรับกับรายรับจริง_แย!B4 -> 3449600 | G6: =IFERROR(B6/F6,0) -> 0.51106882 | H6: =IFERROR(C6/ประมาณการรายจ่ายกับรายจ่ายจริงแ!B4,0) -> 0.47236969
A7: =รายรับรายจ่ายกำไร_ย่อย!A5 -> โรงพยาบาลสัตว์ใหญ่และปศุสัตว์ | B7: =รายรับรายจ่ายกำไร_ย่อย!B5 -> 1008535 | C7: =รายรับรายจ่ายกำไร_ย่อย!C5 -> 1002935 | D7: =รายรับรายจ่ายกำไร_ย่อย!D5 -> 5600 | E7: =IFERROR(D7/B7,0) -> 0.0055526085 | F7: =ประมาณการรายรับกับรายรับจริง_แย!B5 -> 2176700 | G7: =IFERROR(B7/F7,0) -> 0.46333211 | H7: =IFERROR(C7/ประมาณการรายจ่ายกับรายจ่ายจริงแ!B5,0) -> 0.4775881
A8: =รายรับรายจ่ายกำไร_ย่อย!A6 -> ศูนย์สุขภาพช้างและสัตว์ป่า | B8: =รายรับรายจ่ายกำไร_ย่อย!B6 -> 1044605 | C8: =รายรับรายจ่ายกำไร_ย่อย!C6 -> 396333 | D8: =รายรับรายจ่ายกำไร_ย่อย!D6 -> 648272 | E8: =IFERROR(D8/B8,0) -> 0.62059056 | F8: =ประมาณการรายรับกับรายรับจริง_แย!B6 -> 2173300 | G8: =IFERROR(B8/F8,0) -> 0.48065384 | H8: =IFERROR(C8/ประมาณการรายจ่ายกับรายจ่ายจริงแ!B6,0) -> 0.27791389
A9: =รายรับรายจ่ายกำไร_ย่อย!A7 -> ศูนย์ชันเวชศาสตร์ชันสูตรและนวัตกรรมด้านสุขภาพสัตว์ | B9: =รายรับรายจ่ายกำไร_ย่อย!B7 -> 2741058 | C9: =รายรับรายจ่ายกำไร_ย่อย!C7 -> 2740822 | D9: =รายรับรายจ่ายกำไร_ย่อย!D7 -> 236 | E9: =IFERROR(D9/B9,0) -> 8.6098142e-05 | F9: =ประมาณการรายรับกับรายรับจริง_แย!B7 -> 7074000 | G9: =IFERROR(B9/F9,0) -> 0.38748346 | H9: =IFERROR(C9/ประมาณการรายจ่ายกับรายจ่ายจริงแ!B7,0) -> 0.43050011
A10: =รายรับรายจ่ายกำไร_ย่อย!A8 -> ศูนย์ความเป็นเลิศด้านเวชศาสตร์แมว | B10: =รายรับรายจ่ายกำไร_ย่อย!B8 -> 0 | C10: =รายรับรายจ่ายกำไร_ย่อย!C8 -> 0 | D10: =รายรับรายจ่ายกำไร_ย่อย!D8 -> 0 | E10: =IFERROR(D10/B10,0) -> 0 | F10: =ประมาณการรายรับกับรายรับจริง_แย!B8 -> 0 | G10: =IFERROR(B10/F10,0) -> 0 | H10: =IFERROR(C10/ประมาณการรายจ่ายกับรายจ่ายจริงแ!B8,0) -> 0
A11: =รายรับรายจ่ายกำไร_ย่อย!A9 -> Pet CMU (กลุ่มงานบ่มเพาะวิสาหกิจทางสัตวแพทย์) | B11: =รายรับรายจ่ายกำไร_ย่อย!B9 -> 7351957 | C11: =รายรับรายจ่ายกำไร_ย่อย!C9 -> 4155836 | D11: =รายรับรายจ่ายกำไร_ย่อย!D9 -> 3196121 | E11: =IFERROR(D11/B11,0) -> 0.43473064 | F11: =ประมาณการรายรับกับรายรับจริง_แย!B9 -> 7959800 | G11: =IFERROR(B11/F11,0) -> 0.9236359 | H11: =IFERROR(C11/ประมาณการรายจ่ายกับรายจ่ายจริงแ!B9,0) -> 0.58011614
A12: =รายรับรายจ่ายกำไร_ย่อย!A10 -> ศูนย์สัตวแพทย์สาธารณสุขและอาหารปลอดภัยเอเชียแปซิฟิก | B12: =รายรับรายจ่ายกำไร_ย่อย!B10 -> 11985 | C12: =รายรับรายจ่ายกำไร_ย่อย!C10 -> 189641 | D12: =รายรับรายจ่ายกำไร_ย่อย!D10 -> -177656 | E12: =IFERROR(D12/B12,0) -> -14.823196 | F12: =ประมาณการรายรับกับรายรับจริง_แย!B10 -> 526500 | G12: =IFERROR(B12/F12,0) -> 0.022763533 | H12: =IFERROR(C12/ประมาณการรายจ่ายกับรายจ่ายจริงแ!B10,0) -> 0.379282
A13: =รายรับรายจ่ายกำไร_ย่อย!A11 -> ศูนย์เฝ้าระวังสุขภาพหนึ่งเดียว PODD | B13: =รายรับรายจ่ายกำไร_ย่อย!B11 -> 1029558 | C13: =รายรับรายจ่ายกำไร_ย่อย!C11 -> 2307358 | D13: =รายรับรายจ่ายกำไร_ย่อย!D11 -> -1277800 | E13: =IFERROR(D13/B13,0) -> -1.2411151 | F13: =ประมาณการรายรับกับรายรับจริง_แย!B11 -> 4200000 | G13: =IFERROR(B13/F13,0) -> 0.24513286 | H13: =IFERROR(C13/ประมาณการรายจ่ายกับรายจ่ายจริงแ!B11,0) -> 0.5768395
A14: =รายรับรายจ่ายกำไร_ย่อย!A12 -> สำนักงานโรงพยาบาลสัตว์(ศรีบัวบาน) | B14: =รายรับรายจ่ายกำไร_ย่อย!B12 -> 0 | C14: =รายรับรายจ่ายกำไร_ย่อย!C12 -> 0 | D14: =รายรับรายจ่ายกำไร_ย่อย!D12 -> 0 | E14: =IFERROR(D14/B14,0) -> 0 | F14: =ประมาณการรายรับกับรายรับจริง_แย!B12 -> 700000 | G14: =IFERROR(B14/F14,0) -> 0 | H14: =IFERROR(C14/ประมาณการรายจ่ายกับรายจ่ายจริงแ!B12,0) -> 0
A16: Performance highlight | B16: Unit | C16: Metric | D16: Value
A17: Highest Revenue | B17: =INDEX(A4:A14,MATCH(MAX(B4:B14),B4:B14,0)) -> ศูนย์การเรียนรู้และส่งเสริมสุขภาพสัตว์ภาคเหนือ(NOVEL) | C17: ="Revenue" -> Revenue | D17: =MAX(B4:B14) -> 39787921
A18: Highest Expense | B18: =INDEX(A4:A14,MATCH(MAX(C4:C14),C4:C14,0)) -> ศูนย์การเรียนรู้และส่งเสริมสุขภาพสัตว์ภาคเหนือ(NOVEL) | C18: ="Expense" -> Expense | D18: =MAX(C4:C14) -> 31034819
A19: Highest Profit | B19: =INDEX(A4:A14,MATCH(MAX(D4:D14),D4:D14,0)) -> ศูนย์การเรียนรู้และส่งเสริมสุขภาพสัตว์ภาคเหนือ(NOVEL) | C19: ="Operating Result" -> Operating Result | D19: =MAX(D4:D14) -> 8753102
A20: Largest Loss | B20: =INDEX(A4:A14,MATCH(MIN(D4:D14),D4:D14,0)) -> ศูนย์เฝ้าระวังสุขภาพหนึ่งเดียว PODD | C20: ="Operating Result" -> Operating Result | D20: =MIN(D4:D14) -> -1277800
